koko/__init__.py
koko/demo.py
koko/entity_classifier.py
koko/entity_extractor.py
koko/google_document.py
koko/koko-google.py
koko/koko_document.py
koko/koko_eval.py
koko/main.py
koko/matcher.py
koko/parser.py
koko/pykoko.py
koko/query_expander.py
koko/query_processor.py
koko/run_koko.py
koko/scorer.py
koko/segmenter.py
koko/semantic_scorer.py
koko/sentence_decomposer.py
koko/test_document.py
koko/dict/Exercise
koko/dict/Location
pykoko-0.1.8.data/scripts/load_embedding_model.sh
pykoko-0.1.8.dist-info/DESCRIPTION.rst
pykoko-0.1.8.dist-info/METADATA
pykoko-0.1.8.dist-info/RECORD
pykoko-0.1.8.dist-info/WHEEL
pykoko-0.1.8.dist-info/entry_points.txt
pykoko-0.1.8.dist-info/metadata.json
pykoko-0.1.8.dist-info/top_level.txt
