Metadata-Version: 2.0
Name: pykoko
Version: 0.1.8
Summary: KOKO is an easy-to-use entity extraction tool
Home-page: https://github.com/biggorilla-gh/koko
Author: BigGorilla Team
Author-email: behzad@recruit.ai
License: Apache Software License 2.0
Keywords: koko
Platform: UNKNOWN
Classifier: Development Status :: 2 - Pre-Alpha
Classifier: Intended Audience :: Developers
Classifier: License :: OSI Approved :: Apache Software License
Classifier: Natural Language :: English
Classifier: Programming Language :: Python :: 3
Classifier: Programming Language :: Python :: 3.3
Classifier: Programming Language :: Python :: 3.4
Classifier: Programming Language :: Python :: 3.5
Classifier: Programming Language :: Python :: 3.6
Requires-Dist: Click (>=6.0)
Requires-Dist: google-api-python-client
Requires-Dist: httplib2
Requires-Dist: langdetect
Requires-Dist: numpy
Requires-Dist: progressbar2
Requires-Dist: requests
Requires-Dist: spacy
Requires-Dist: unidecode
